stark_middlewares/__init__.py
stark_middlewares/middlewares.py
stark_middlewares-0.4.dist-info/LICENCE.txt
stark_middlewares-0.4.dist-info/METADATA
stark_middlewares-0.4.dist-info/WHEEL
stark_middlewares-0.4.dist-info/top_level.txt
stark_middlewares-0.4.dist-info/RECORD
