Metadata-Version: 2.1
Name: stark-middlewares
Version: 0.4
Summary: Stark Middlewares
Home-page: UNKNOWN
Author: Stark Digital Media Services Pvt. Ltd.
Author-email: starkengg81@gmail.com
License: UNKNOWN
Keywords: stark,stark-middlewares,middlewares,stark_middlewares
Platform: UNKNOWN
Classifier: Operating System :: OS Independent
Classifier: License :: OSI Approved :: MIT License
Classifier: Programming Language :: Python :: 3
Requires-Python: >=3.6
Requires-Dist: requests
